DataSets/__init__.py
DataSets/getdata.py
Metrics/Metrics.py
Metrics/__init__.py
groundingdino/_C.cp310-win_amd64.pyd
groundingdino/__init__.py
groundingdino/config/GroundingDINO_SwinB_cfg.py
groundingdino/config/GroundingDINO_SwinT_OGC.py
groundingdino/config/__init__.py
groundingdino/datasets/__init__.py
groundingdino/datasets/cocogrounding_eval.py
groundingdino/datasets/transforms.py
groundingdino/models/__init__.py
groundingdino/models/registry.py
groundingdino/models/GroundingDINO/__init__.py
groundingdino/models/GroundingDINO/bertwarper.py
groundingdino/models/GroundingDINO/fuse_modules.py
groundingdino/models/GroundingDINO/groundingdino.py
groundingdino/models/GroundingDINO/ms_deform_attn.py
groundingdino/models/GroundingDINO/transformer.py
groundingdino/models/GroundingDINO/transformer_vanilla.py
groundingdino/models/GroundingDINO/utils.py
groundingdino/models/GroundingDINO/backbone/__init__.py
groundingdino/models/GroundingDINO/backbone/backbone.py
groundingdino/models/GroundingDINO/backbone/position_encoding.py
groundingdino/models/GroundingDINO/backbone/swin_transformer.py
groundingdino/models/GroundingDINO/csrc/cuda_version.cu
groundingdino/models/GroundingDINO/csrc/vision.cpp
groundingdino/models/GroundingDINO/csrc/MsDeformAttn/ms_deform_attn.h
groundingdino/models/GroundingDINO/csrc/MsDeformAttn/ms_deform_attn_cpu.cpp
groundingdino/models/GroundingDINO/csrc/MsDeformAttn/ms_deform_attn_cpu.h
groundingdino/models/GroundingDINO/csrc/MsDeformAttn/ms_deform_attn_cuda.cu
groundingdino/models/GroundingDINO/csrc/MsDeformAttn/ms_deform_attn_cuda.h
groundingdino/models/GroundingDINO/csrc/MsDeformAttn/ms_deform_im2col_cuda.cuh
groundingdino/util/__init__.py
groundingdino/util/box_ops.py
groundingdino/util/get_tokenlizer.py
groundingdino/util/inference.py
groundingdino/util/logger.py
groundingdino/util/misc.py
groundingdino/util/slconfig.py
groundingdino/util/slio.py
groundingdino/util/time_counter.py
groundingdino/util/utils.py
groundingdino/util/visualizer.py
groundino_samnet-0.5.13.dist-info/LICENSE
groundino_samnet-0.5.13.dist-info/METADATA
groundino_samnet-0.5.13.dist-info/WHEEL
groundino_samnet-0.5.13.dist-info/top_level.txt
groundino_samnet-0.5.13.dist-info/RECORD
