Metadata-Version: 2.1
Name: groundino_samnet
Version: 0.5.13
Summary: A SAM model with GroundingDINO model for feet segmentation
Home-page: https://github.com/ladmepaz/GSAMnet
Author: Wilhelm David Buitrago Garcia
License: Apache License
Project-URL: GSAMnet, https://github.com/ladmepaz/GSAMnet
Classifier: Programming Language :: Python :: 3
Classifier: Programming Language :: Python :: 3.10
License-File: LICENSE
Requires-Dist: torch==2.4.1+cu121
Requires-Dist: torchvision==0.19.1+cu121
Requires-Dist: torchaudio==2.4.1+cu121
Requires-Dist: numpy==1.26.4
Requires-Dist: transformers==4.42.4
Requires-Dist: huggingface-hub==0.23.5
Requires-Dist: addict==2.4.0
Requires-Dist: opencv-python==4.10.0.84
Requires-Dist: pycocotools
Requires-Dist: yapf
Requires-Dist: timm
Requires-Dist: supervision==0.22.0
Requires-Dist: tqdm>=4.66.1
Requires-Dist: scikit-learn
Requires-Dist: hydra-core>=1.3.2
Requires-Dist: iopath>=0.1.10
Requires-Dist: ninja
Requires-Dist: kaggle
Requires-Dist: pandas
